brwne_cli/__init__.py
brwne_cli/arts.py
brwne_cli/commands/A10_submit.py
brwne_cli/commands/A11_clone.py
brwne_cli/commands/A12_switch.py
brwne_cli/commands/A13_checkout.py
brwne_cli/commands/A1_init.py
brwne_cli/commands/A2_add.py
brwne_cli/commands/A3_commit.py
brwne_cli/commands/A4_status.py
brwne_cli/commands/A5_map.py
brwne_cli/commands/A6_branch.py
brwne_cli/commands/A7_push.py
brwne_cli/commands/A8_get_cautions.py
brwne_cli/commands/A9_cascade.py
brwne_cli/commands/auth.py
brwne_cli/fireEngine.py
brwne_cli/gitEngine.py
brwne_cli/utils/ANSI_Colors.py
brwne_cli/utils/get_repoID_from_local.py
brwne_cli/utils/pre_command_decorator.py
brwne_cli-0.1.2.dist-info/METADATA
brwne_cli-0.1.2.dist-info/WHEEL
brwne_cli-0.1.2.dist-info/entry_points.txt
brwne_cli-0.1.2.dist-info/RECORD
