Metadata-Version: 2.1
Name: brwne-cli
Version: 0.1.2
Summary: 
License: cannot_describe
Author: PirateShip Pte. Ltd.
Author-email: team@thepirateship.net
Requires-Python: >=3.13,<4.0
Classifier: License :: Other/Proprietary License
Classifier: Programming Language :: Python :: 3
Classifier: Programming Language :: Python :: 3.13
Requires-Dist: click (>=8.1.7,<9.0.0)
Requires-Dist: inquirerpy (>=0.3.4,<0.4.0)
Requires-Dist: keyring (>=25.5.0,<26.0.0)
Requires-Dist: pydantic (>=2.9.2,<3.0.0)
Requires-Dist: requests (>=2.32.3,<3.0.0)
